tag_func.py
williballenthin_tag_func_ida_plugin-0.1.0.dist-info/METADATA
williballenthin_tag_func_ida_plugin-0.1.0.dist-info/WHEEL
williballenthin_tag_func_ida_plugin-0.1.0.dist-info/entry_points.txt
williballenthin_tag_func_ida_plugin-0.1.0.dist-info/top_level.txt
williballenthin_tag_func_ida_plugin-0.1.0.dist-info/RECORD
