Metadata-Version: 2.4
Name: williballenthin-tag-func-ida-plugin
Version: 0.1.0
Summary: IDA Pro plugin for tagging functions into folders
Author-email: Willi Ballenthin <willi.ballenthin@gmail.com>
License-Expression: Apache-2.0
Requires-Python: >=3.9
